odoo/addons/endpoint/README.rst
odoo/addons/endpoint/__init__.py
odoo/addons/endpoint/__manifest__.py
odoo/addons/endpoint/hooks.py
odoo/addons/endpoint/controllers/__init__.py
odoo/addons/endpoint/controllers/main.py
odoo/addons/endpoint/demo/endpoint_demo.xml
odoo/addons/endpoint/i18n/endpoint.pot
odoo/addons/endpoint/i18n/fr.po
odoo/addons/endpoint/i18n/it.po
odoo/addons/endpoint/migrations/14.0.1.1.0/pre-migrate.py
odoo/addons/endpoint/migrations/14.0.2.0.0/post-migrate.py
odoo/addons/endpoint/models/__init__.py
odoo/addons/endpoint/models/endpoint_endpoint.py
odoo/addons/endpoint/models/endpoint_mixin.py
odoo/addons/endpoint/readme/CONFIGURE.rst
odoo/addons/endpoint/readme/CONTRIBUTORS.rst
odoo/addons/endpoint/readme/DESCRIPTION.rst
odoo/addons/endpoint/readme/ROADMAP.rst
odoo/addons/endpoint/security/ir.model.access.csv
odoo/addons/endpoint/security/ir_rule.xml
odoo/addons/endpoint/static/description/icon.png
odoo/addons/endpoint/static/description/index.html
odoo/addons/endpoint/tests/__init__.py
odoo/addons/endpoint/tests/common.py
odoo/addons/endpoint/tests/test_endpoint.py
odoo/addons/endpoint/tests/test_endpoint_controller.py
odoo/addons/endpoint/views/endpoint_view.xml
odoo14_addon_endpoint-14.0.2.4.0.dist-info/METADATA
odoo14_addon_endpoint-14.0.2.4.0.dist-info/WHEEL
odoo14_addon_endpoint-14.0.2.4.0.dist-info/top_level.txt
odoo14_addon_endpoint-14.0.2.4.0.dist-info/RECORD
